__init__.py
investlife.py
invest_life-0.1.3.dist-info/LICENSE
invest_life-0.1.3.dist-info/METADATA
invest_life-0.1.3.dist-info/WHEEL
invest_life-0.1.3.dist-info/top_level.txt
invest_life-0.1.3.dist-info/RECORD
